flexdown/__init__.py
flexdown/cli.py
flexdown/constants.py
flexdown/document.py
flexdown/flexdown.py
flexdown/namespace.py
flexdown/types.py
flexdown/utils.py
flexdown/blocks/__init__.py
flexdown/blocks/alert_block.py
flexdown/blocks/block.py
flexdown/blocks/code_block.py
flexdown/blocks/demo_block.py
flexdown/blocks/eval_block.py
flexdown/blocks/exec_block.py
flexdown/blocks/markdown_block.py
flexdown/ui/__init__.py
flexdown/ui/layout.py
flexdown/ui/components/__init__.py
flexdown/ui/components/content.py
flexdown/ui/components/navbar.py
flexdown/ui/components/sidebar.py
flexdown/ui/components/toc.py
flexdown-0.2.5.dist-info/METADATA
flexdown-0.2.5.dist-info/WHEEL
flexdown-0.2.5.dist-info/entry_points.txt
flexdown-0.2.5.dist-info/RECORD
