Metadata-Version: 2.4
Name: flexdown
Version: 0.2.5
Summary: Write interactive documentation with Markdown and Python.
Author-email: Nikhil Rao <nikhil@reflex.dev>, Thomas Brandého <thomas@reflex.dev>
Requires-Python: <4.0,>=3.10
Requires-Dist: black>=25.0
Requires-Dist: mistletoe>=1.4.0
Requires-Dist: pyyaml>=6.0.1
Requires-Dist: reflex>=0.7.1
